dbt/adapters/doris/__init__.py
dbt/adapters/doris/__version__.py
dbt/adapters/doris/column.py
dbt/adapters/doris/connections.py
dbt/adapters/doris/doris_column_item.py
dbt/adapters/doris/impl.py
dbt/adapters/doris/relation.py
dbt/include/doris/__init__.py
dbt/include/doris/dbt_project.yml
dbt/include/doris/profile_template.yml
dbt/include/doris/sample_profiles.yml
dbt/include/doris/macros/adapters/columns.sql
dbt/include/doris/macros/adapters/freshness.sql
dbt/include/doris/macros/adapters/metadata.sql
dbt/include/doris/macros/adapters/relation.sql
dbt/include/doris/macros/adapters/schema.sql
dbt/include/doris/macros/materializations/incremental/help.sql
dbt/include/doris/macros/materializations/incremental/incremental.sql
dbt/include/doris/macros/materializations/partition/helpers.sql
dbt/include/doris/macros/materializations/partition/partition.sql
dbt/include/doris/macros/materializations/partition/replace.sql
dbt/include/doris/macros/materializations/seed/helpers.sql
dbt/include/doris/macros/materializations/snapshot/snapshot.sql
dbt/include/doris/macros/materializations/snapshot/strategies.sql
dbt/include/doris/macros/materializations/table/create_table_as.sql
dbt/include/doris/macros/materializations/table/table.sql
dbt/include/doris/macros/materializations/view/create_view_as.sql
dbt/include/doris/macros/materializations/view/view.sql
dbt_doris-0.4.0.dist-info/licenses/LICENSE
dbt_doris-0.4.0.dist-info/METADATA
dbt_doris-0.4.0.dist-info/WHEEL
dbt_doris-0.4.0.dist-info/top_level.txt
dbt_doris-0.4.0.dist-info/RECORD
