Metadata-Version: 2.4
Name: dbt-doris
Version: 0.4.0
Summary: The doris adapter plugin for dbt 
Home-page: https://github.com/apache/doris/tree/master/extension/dbt-doris
Author: catpineapple,JNSimba
Author-email: catpineapple@apache.org
Requires-Python: >=3.9
License-File: LICENSE
Requires-Dist: dbt-core>=1.8.0
Requires-Dist: mysql-connector-python<8.3,>=8.0.0
Requires-Dist: urllib3~=1.0
Dynamic: author
Dynamic: author-email
Dynamic: description
Dynamic: home-page
Dynamic: license-file
Dynamic: requires-dist
Dynamic: requires-python
Dynamic: summary
